CHANGES.rst
LICENSE
README.rst
setup.py
minesoft_patbase_client.egg-info/PKG-INFO
minesoft_patbase_client.egg-info/SOURCES.txt
minesoft_patbase_client.egg-info/dependency_links.txt
minesoft_patbase_client.egg-info/entry_points.txt
minesoft_patbase_client.egg-info/not-zip-safe
minesoft_patbase_client.egg-info/requires.txt
minesoft_patbase_client.egg-info/top_level.txt
patbase/__init__.py
patbase/client.py
patbase/command.py
patbase/exceptions.py
patbase/util.py