Metadata-Version: 2.1
Name: minesoft-patbase-client
Version: 0.1.0
Summary: minesoft-patbase-client is a client library for accessing the Minesoft PatBase REST API
Home-page: https://github.com/ip-tools/minesoft-patbase-client
Author: Andreas Motl
Author-email: andreas.motl@ip-tools.org
License: AGPL 3, EUPL 1.2
Keywords: patent information minesoft patbase rest api client bulk data download import interface research search opendata xml json
Platform: UNKNOWN
Classifier: Development Status :: 3 - Alpha
Classifier: Environment :: Console
Classifier: Environment :: Web Environment
Classifier: Intended Audience :: Developers
Classifier: Intended Audience :: Education
Classifier: Intended Audience :: End Users/Desktop
Classifier: Intended Audience :: Information Technology
Classifier: Intended Audience :: Legal Industry
Classifier: Intended Audience :: Manufacturing
Classifier: Intended Audience :: Science/Research
Classifier: License :: OSI Approved :: European Union Public Licence 1.2 (EUPL 1.2)
Classifier: License :: OSI Approved :: GNU Affero General Public License v3 or later (AGPLv3+)
Classifier: Natural Language :: English
Classifier: Operating System :: MacOS :: MacOS X
Classifier: Operating System :: POSIX :: Linux
Classifier: Programming Language :: Python
Classifier: Topic :: Internet :: WWW/HTTP
Classifier: Topic :: Scientific/Engineering
Classifier: Topic :: Software Development :: Libraries
Classifier: Topic :: System :: Archiving
Classifier: Topic :: Text Processing
Classifier: Topic :: Utilities
Provides-Extra: release
Provides-Extra: documentation
